Workbook

Sheet Sales Data
A1: Order_ID | B1: Order_Date | C1: Region | D1: Category | E1: Product | F1: Quantity | G1: Unit_Price | H1: Unit_Cost | I1: REVENUE | J1: TOTAL COST | K1: PROFIT
A2: ORD001 | B2: 46023 | C2: South | D2: Electronics | E2: Laptop | F2: 2 | G2: 50000 | H2: 42000 | I2: =F2*G2 -> 100000 | J2: =F2*H2 -> 84000 | K2: 16000
A3: ORD002 | B3: 46025 | C3: North | D3: Furniture | E3: Chair | F3: 5 | G3: 2500 | H3: 1800 | I3: =F3*G3 -> 12500 | J3: =F3*H3 -> 9000 | K3: =I3-J3 -> 3500
A4: ORD003 | B4: 46027 | C4: East | D4: Electronics | E4: Mouse | F4: 10 | G4: 500 | H4: 300 | I4: =F4*G4 -> 5000 | J4: =F4*H4 -> 3000 | K4: =I4-J4 -> 2000
A5: ORD004 | B5: 46030 | C5: West | D5: Furniture | E5: Table | F5: 3 | G5: 8000 | H5: 6000 | I5: =F5*G5 -> 24000 | J5: =F5*H5 -> 18000 | K5: =I5-J5 -> 6000
A6: ORD005 | B6: 46032 | C6: South | D6: Accessories | E6: Keyboard | F6: 6 | G6: 1200 | H6: 800 | I6: =F6*G6 -> 7200 | J6: =F6*H6 -> 4800 | K6: =I6-J6 -> 2400
A7: ORD006 | B7: 46034 | C7: North | D7: Electronics | E7: Monitor | F7: 4 | G7: 12000 | H7: 9500 | I7: =F7*G7 -> 48000 | J7: =F7*H7 -> 38000 | K7: =I7-J7 -> 10000
A8: ORD007 | B8: 46037 | C8: East | D8: Accessories | E8: Headphones | F8: 8 | G8: 2000 | H8: 1300 | I8: =F8*G8 -> 16000 | J8: =F8*H8 -> 10400 | K8: =I8-J8 -> 5600
A9: ORD008 | B9: 46040 | C9: West | D9: Electronics | E9: Laptop | F9: 1 | G9: 50000 | H9: 42000 | I9: =F9*G9 -> 50000 | J9: =F9*H9 -> 42000 | K9: =I9-J9 -> 8000
A10: ORD009 | B10: 46042 | C10: South | D10: Furniture | E10: Chair | F10: 4 | G10: 2500 | H10: 1800 | I10: =F10*G10 -> 10000 | J10: =F10*H10 -> 7200 | K10: =I10-J10 -> 2800
A11: ORD010 | B11: 46044 | C11: North | D11: Accessories | E11: Keyboard | F11: 10 | G11: 1200 | H11: 800 | I11: =F11*G11 -> 12000 | J11: =F11*H11 -> 8000 | K11: =I11-J11 -> 4000
A12: ORD011 | B12: 46055 | C12: East | D12: Electronics | E12: Monitor | F12: 3 | G12: 12000 | H12: 9500 | I12: =F12*G12 -> 36000 | J12: =F12*H12 -> 28500 | K12: =I12-J12 -> 7500
A13: ORD012 | B13: 46058 | C13: West | D13: Accessories | E13: Mouse | F13: 15 | G13: 500 | H13: 300 | I13: =F13*G13 -> 7500 | J13: =F13*H13 -> 4500 | K13: =I13-J13 -> 3000
A14: ORD013 | B14: 46061 | C14: South | D14: Electronics | E14: Laptop | F14: 2 | G14: 50000 | H14: 42000 | I14: =F14*G14 -> 100000 | J14: =F14*H14 -> 84000 | K14: =I14-J14 -> 16000
... A21: ORD020 | B21: 46088 | C21: West | D21: Electronics | E21: Monitor | F21: 5 | G21: 12000 | H21: 9500 | I21: =F21*G21 -> 60000 | J21: =F21*H21 -> 47500 | K21: =I21-J21 -> 12500

Sheet sa

Sheet Analysis
A1: SALES PERFORMANCE ANALYSIS | B1: Column1
A2: revenue | B2: =SUM('Sales Data'!I2:I21) -> 620800 | D2: Region | E2: regional revenue
A3: cost | B3: =SUM('Sales Data'!J2:J21) -> 490600 | D3: South | E3: =SUMIFS('Sales Data'!$I$2:$I$21,'Sales Data'!$C$2:$C$21,D3) -> 226800
A4: Profit | B4: =SUM('Sales Data'!K2:K21) -> 114200 | D4: North | E4: =SUMIFS('Sales Data'!$I$2:$I$21,'Sales Data'!$C$2:$C$21,D4) -> 138500
A5: Total Orders | B5: =COUNTA('Sales Data'!A2:A21) -> 20 | D5: East | E5: =SUMIFS('Sales Data'!$I$2:$I$21,'Sales Data'!$C$2:$C$21,D5) -> 99000
A6: Total Units Sold | B6: =SUM('Sales Data'!F2:F21) -> 104 | D6: West | E6: =SUMIFS('Sales Data'!$I$2:$I$21,'Sales Data'!$C$2:$C$21,D6) -> 156500
A7: average order value | B7: =AVERAGE('Sales Data'!I2:I21) -> 31040
A8: Profit Margin | B8: =B4/B2 -> 0.18395619
D10: Month | E10: monthly revenue
A11: Category | B11: Total Profit | D11: Jan | E11: =SUMIFS('Sales Data'!$I$2:$I$21,'Sales Data'!$B$2:$B$21,">="&DATE(2026,1,1),'Sales Data'!$B$2:$B$21,"<"&DATE(2026,2,1)) -> 284700
A12: Electronics | B12: =SUMIF('Sales Data'!D:D,A12,'Sales Data'!K:K) -> 64000 | D12: Feb | E12: =SUMIFS('Sales Data'!$I$2:$I$21,'Sales Data'!$B$2:$B$21,">="&DATE(2026,2,1),'Sales Data'!$B$2:$B$21,"<"&DATE(2026,3,1)) -> 244100
A13: Furniture | B13: =SUMIF('Sales Data'!D:D,A13,'Sales Data'!K:K) -> 28500 | D13: Mar | E13: =SUMIFS('Sales Data'!$I$2:$I$21,'Sales Data'!$B$2:$B$21,">="&DATE(2026,3,1),'Sales Data'!$B$2:$B$21,"<"&DATE(2026,4,1)) -> 92000
A14: Accessories | B14: =SUMIF('Sales Data'!D:D,A14,'Sales Data'!K:K) -> 21700
